{
   "abstract" : "Model Context Protocol server for CPAN Testers data",
   "author" : [
      "Doug Bell <preaction@cpan.org>"
   ],
   "dynamic_config" : 0,
   "generated_by" : "Dist::Zilla version 6.036, CPAN::Meta::Converter version 2.150010",
   "license" : [
      "perl_5"
   ],
   "meta-spec" : {
      "url" : "http://search.cpan.org/perldoc?CPAN::Meta::Spec",
      "version" : 2
   },
   "name" : "CPAN-Testers-MCP",
   "no_index" : {
      "directory" : [
         "eg",
         "examples",
         "inc",
         "share",
         "t",
         "xt"
      ]
   },
   "prereqs" : {
      "configure" : {
         "requires" : {
            "ExtUtils::MakeMaker" : "0"
         }
      },
      "runtime" : {
         "requires" : {
            "Future::AsyncAwait" : "0.52",
            "Log::Any" : "1.719",
            "Log::Any::Adapter::OpenTelemetry" : "0",
            "MCP" : "0.08",
            "Mojolicious" : "9",
            "perl" : "5.040"
         }
      },
      "test" : {
         "recommends" : {
            "CPAN::Meta" : "2.120900"
         },
         "requires" : {
            "ExtUtils::MakeMaker" : "0",
            "File::Spec" : "0",
            "IO::Handle" : "0",
            "IPC::Open3" : "0",
            "Test2::V1" : "1.302219",
            "Test::More" : "0"
         }
      }
   },
   "provides" : {
      "CPAN::Testers::MCP" : {
         "file" : "lib/CPAN/Testers/MCP.pm",
         "version" : "0.001"
      },
      "CPAN::Testers::MCP::Server" : {
         "file" : "lib/CPAN/Testers/MCP/Server.pm",
         "version" : "0.001"
      }
   },
   "release_status" : "stable",
   "resources" : {
      "bugtracker" : {
         "web" : "https://github.com/cpan-testers/mcp/issues"
      },
      "homepage" : "https://github.com/cpan-testers/mcp",
      "repository" : {
         "type" : "git",
         "url" : "https://github.com/cpan-testers/mcp.git",
         "web" : "https://github.com/cpan-testers/mcp"
      }
   },
   "version" : "0.001",
   "x_authority" : "cpan:PREACTION",
   "x_generated_by_perl" : "v5.42.0",
   "x_serialization_backend" : "Cpanel::JSON::XS version 4.40",
   "x_spdx_expression" : "Artistic-1.0-Perl OR GPL-1.0-or-later"
}

